README.rst
setup.py
pharaoh/__init__.py
pharaoh/cmdline.py
pharaoh/gunicorn_application.py
pharaoh/manage.py
pharaoh/mongo_to_po.py
pharaoh/po_to_mongo.py
pharaoh/serialization.py
pharaoh/utils.py
pharaoh.egg-info/PKG-INFO
pharaoh.egg-info/SOURCES.txt
pharaoh.egg-info/dependency_links.txt
pharaoh.egg-info/entry_points.txt
pharaoh.egg-info/requires.txt
pharaoh.egg-info/top_level.txt
pharaoh/app/__init__.py
pharaoh/app/filters.py
pharaoh/app/flask_app.py
pharaoh/app/models.py
pharaoh/app/views.py
test/__init__.py
test/test_verifier.py